{
  "id": "36691916",
  "link": "https://www.njuskalo.hr/nekretnine/zanimljiva-kuca-velika-gorica-140m2-oglas-36691916",
  "lokacija": {
    "lat": 45.71239425765,
    "lng": 16.080514861279,
    "approximate": true
  },
  "naslov": "Zanimljiva kuća, Velika Gorica, 140m2 (prodaja)",
  "cijena": "250.000 €",
  "Lokacija": "Zagrebačka, Velika Gorica, Centar",
  "Tip kuće": "U nizu",
  "Broj etaža": "Katnica",
  "Broj soba": "4",
  "Stambena površina": "120,00 m²",
  "Površina okućnice": "141,00 m²",
  "Balkon/Lođa/Terasa": "Balkon, Terasa",
  "Šifra objekta": "ZG67485",
  "opis": "Prodaje se obiteljska kuća u nizu, građena s konstrukcijom od armiranog betona, uz potpuno novi krov i konstrukciju. Kuća je savršena za obitelj i nudi prostran i funkcionalan raspored na tri razine. Detalji kuće: Prizemlje: Uređeno prizemlje uključuje: Kuhinju, Toalet, Prostrani dnevni boravak s izlazom na veliki, pažljivo održavani vrt, idealan za druženja, roštiljanja i opuštanje tijekom cijele godine. Prvi kat: Dvije spavaće sobe (veća okrenuta prema vrtu, manja prema ulici), Hodnik, Kupaonica. Potkrovlje: Potkrovlje je u roh-bau fazi, s mogućnošću izvedbe dodatne spavaće sobe i kupaonice. Iako je upisana površina 120 m2 u naravi nalazimo površinu od 140 m2. Dvorište: U predivnom vrtu nalazi se drvena kućica za odmor ili spremište. Mogućnosti dodatne gradnje: Na zemljištu postoji mogućnost gradnje garaže za dva automobila ili manjeg objekta do 80 m² (podrum + prizemlje). Trenutno su osigurana dva parkirna mjesta. Posebna pogodnost: Vlasnici prihvaćaju zamjenu za manju nekretninu uz uplatu razlike u cijeni! Lokacija i prilike: Kuća se nalazi na mirnoj lokaciji, idealnoj za obiteljski život, s blizinom svih važnih sadržaja. Ne propustite priliku za razgledavanje ove nekretnine koja nudi nevjerojatan potencijal za ugodan život! Za dodatne informacije i dogovor termina razgledavanja, stojim na raspolaganju Aurelija Kaniški: 00385 99 547 2989 aurelija.kaniski@dogma-nekretnine.com ID KOD AGENCIJE: ZG67485 Dogma Zagreb Tel: 01/647-3011 E-mail: zagreb@dogma-nekretnine.com www.dogma-zagreb.com Aurelija Kaniški Agent s licencom Mob: 099/547-2989 Tel: 042/562-017 E-mail: aurelija.kaniski@dogma-nekretnine.com www.dogma-nekretnine.com",
  "Grijanje": [
    "Sustav grijanja: Etažno plinsko centralno"
  ],
  "Podaci o objektu": [
    "Gradski plin",
    "Gradski vodovod",
    "Gradska kanalizacija"
  ],
  "Dozvole i potvrde": [
    "Vlasnički list",
    "Građevinska dozvola"
  ],
  "Kupaonica i WC": [
    "Broj kupaonica s WC-om: 3",
    "Broj WC-a: 1"
  ],
  "Ostali objekti i površine": [
    "Dvorište/vrt",
    "Spremište/šupa",
    "Vrtna kućica"
  ],
  "naziv_agencije": "Dogma nekretnine",
  "profil_agencije": "https://www.njuskalo.hr/agencija/dogma-nekretnine",
  "email_agencije": "info@dogma-nekretnine.com",
  "adresa_agencije": "Adresa:Primorsko-goranska, Hrvatska",
  "telefon": "01 6473 011",
  "oglas_objavljen": "28.07.2025. u 12:20",
  "do_isteka": "do prodaje",
  "oglas_prikazan": "28680 puta",
  "slike": [
    "https://www.njuskalo.hr/image-xlsize/nekretnine/zanimljiva-kuca-velika-gorica-140m2-slika-252971476.jpg",
    "https://www.njuskalo.hr/image-xlsize/nekretnine/zanimljiva-kuca-velika-gorica-140m2-slika-252971477.jpg",
    "https://www.njuskalo.hr/image-xlsize/nekretnine/zanimljiva-kuca-velika-gorica-140m2-slika-252971478.jpg",
    "https://www.njuskalo.hr/image-xlsize/nekretnine/zanimljiva-kuca-velika-gorica-140m2-slika-252971479.jpg",
    "https://www.njuskalo.hr/image-xlsize/nekretnine/zanimljiva-kuca-velika-gorica-140m2-slika-252971480.jpg",
    "https://www.njuskalo.hr/image-xlsize/nekretnine/zanimljiva-kuca-velika-gorica-140m2-slika-252971481.jpg",
    "https://www.njuskalo.hr/image-xlsize/nekretnine/zanimljiva-kuca-velika-gorica-140m2-slika-252971482.jpg",
    "https://www.njuskalo.hr/image-xlsize/nekretnine/zanimljiva-kuca-velika-gorica-140m2-slika-252971483.jpg"
  ]
}