{
  "id": "38730754",
  "link": "https://www.njuskalo.hr/nekretnine/kuca-gornje-brezno-187.00-m2-oglas-38730754",
  "lokacija": {
    "lat": 46.192560818135,
    "lng": 15.664768738083,
    "approximate": true
  },
  "naslov": "Kuća: Gornje Brezno, 72.00 m2 (prodaja)",
  "cijena": "5.401 €",
  "Lokacija": "Krapinsko-zagorska, Hum Na Sutli, Gornje Brezno",
  "Tip kuće": "Samostojeća",
  "Broj etaža": "Katnica",
  "Broj soba": "3",
  "Stambena površina": "72,00 m²",
  "Površina okućnice": "187,00 m²",
  "Šifra objekta": "S102 TZ",
  "Mogućnost zamjene": "Nije moguća zamjena za drugu nekretninu",
  "opis": "Nekretnine izgrađena na čkbr. 35 kuća br. 69 i dvorište, površine 52 čhv, upisana u z.k.ul. 1210 k.o. Brezno. U posjedu.",
  "naziv_agencije": "DDM REO Adria d.o.o.",
  "profil_agencije": "https://www.njuskalo.hr/tvrtka/ddm-reo-adria",
  "adresa_agencije": "Adresa:Grad Zagreb, Hrvatska",
  "telefon": "091 182 2220",
  "oglas_objavljen": "21.07.2025. u 15:24",
  "do_isteka": "do prodaje",
  "oglas_prikazan": "24724 puta",
  "slike": [
    "https://www.njuskalo.hr/image-xlsize/nekretnine/kuca-gornje-brezno-187.00-m2-slika-181512694.jpg",
    "https://www.njuskalo.hr/image-xlsize/nekretnine/kuca-gornje-brezno-187.00-m2-slika-181512697.jpg",
    "https://www.njuskalo.hr/image-xlsize/nekretnine/kuca-gornje-brezno-187.00-m2-slika-181512691.jpg",
    "https://www.njuskalo.hr/image-xlsize/nekretnine/kuca-gornje-brezno-187.00-m2-slika-181512692.jpg",
    "https://www.njuskalo.hr/image-xlsize/nekretnine/kuca-gornje-brezno-187.00-m2-slika-181512696.jpg",
    "https://www.njuskalo.hr/image-xlsize/nekretnine/kuca-gornje-brezno-187.00-m2-slika-181512698.jpg",
    "https://www.njuskalo.hr/image-xlsize/nekretnine/kuca-gornje-brezno-187.00-m2-slika-181512699.jpg",
    "https://www.njuskalo.hr/image-xlsize/nekretnine/kuca-gornje-brezno-187.00-m2-slika-181512693.jpg"
  ]
}