{
  "id": "41281162",
  "link": "https://www.njuskalo.hr/nekretnine/kuca-obnovu-v-rakovica-55-m2-29.000-oglas-41281162",
  "lokacija": {
    "lat": 45.776668,
    "lng": 15.717058,
    "approximate": false
  },
  "naslov": "Kuća za obnovu, V. Rakovica, 55 m2, 35.000 € (prodaja)",
  "cijena": "35.000 €",
  "Lokacija": "Zagrebačka, Samobor - Okolica, Mala Rakovica",
  "Tip kuće": "Samostojeća",
  "Broj etaža": "Prizemnica",
  "Broj soba": "2",
  "Stambena površina": "55,00 m²",
  "Godina izgradnje": "1930.",
  "Šifra objekta": "300611005-61",
  "opis": "Prodaje se stara kuća za obnovu, prizemnica tlocrtne površine 55 m2, na parceli od 672 m2, po cijeni od 35.000 €. Kuća je u naselju Koletići, V. Rakovica. Po postojećim dozvolama, moguća je gradnja dvije manje kuće od oko 55 m2. Jedna kućica se vidi na slikama, druga je srušena, ali ima valjane dozvole za gradnju u navedenim gabaritima. Udaljena od centra Samobora tek nekoliko minuta vožnje, blizu svih sadržaja potrebnih za život. Objekt je za generalnu rekonstrukciju, ili rušenje, ovisno o afinitetima i mogućnostima kupca. Građena je oko 1930. godine, uredno vlasništvo (jedan vlasnik 1/1), asfaltirani put do parcele, ima priključak struje, a voda je uz parcelu. Za sve dodatne informacije molim da nam se obratite na: +385 91 278 9999 +385 1 211 0212 RE/MAX CITY 2 Mlinska 23, Samobor Sve informacije dane od agenta smatraju se važećim, no moraju se zasebno procijeniti.",
  "Grijanje": [
    "Sustav grijanja: Nema sustav grijanja"
  ],
  "naziv_agencije": "RE/MAX City 2 Samobor",
  "profil_agencije": "https://www.njuskalo.hr/agencija/remax-city2",
  "email_agencije": "city2@remax.hr",
  "adresa_agencije": "Adresa:Grad Zagreb, Hrvatska",
  "telefon": null,
  "oglas_objavljen": "17.06.2025. u 09:17",
  "do_isteka": "do prodaje",
  "oglas_prikazan": "7535 puta",
  "slike": [
    "https://www.njuskalo.hr/image-xlsize/nekretnine/kuca-obnovu-v-rakovica-55-m2-29.000-slika-247522091.jpg",
    "https://www.njuskalo.hr/image-xlsize/nekretnine/kuca-obnovu-v-rakovica-55-m2-29.000-slika-247522092.jpg",
    "https://www.njuskalo.hr/image-xlsize/nekretnine/kuca-obnovu-v-rakovica-55-m2-29.000-slika-247522093.jpg",
    "https://www.njuskalo.hr/image-xlsize/nekretnine/kuca-obnovu-v-rakovica-55-m2-29.000-slika-247522095.jpg",
    "https://www.njuskalo.hr/image-xlsize/nekretnine/kuca-obnovu-v-rakovica-55-m2-29.000-slika-247522097.jpg",
    "https://www.njuskalo.hr/image-xlsize/nekretnine/kuca-obnovu-v-rakovica-55-m2-29.000-slika-247522099.jpg"
  ]
}