{
  "id": "41624001",
  "link": "https://www.njuskalo.hr/nekretnine/istra-labin-moderna-novogradnja-bazenom-oglas-41624001",
  "lokacija": {
    "lat": 45.094959568609,
    "lng": 14.124438820112,
    "approximate": true
  },
  "naslov": "ISTRA, LABIN, MODERNA NOVOGRADNJA S BAZENOM (prodaja)",
  "cijena": "615.000 €",
  "Lokacija": "Istarska, Labin, Labin",
  "Tip kuće": "Samostojeća",
  "Broj etaža": "Katnica",
  "Broj soba": "4",
  "Stambena površina": "182,00 m²",
  "Površina okućnice": "1.280,00 m²",
  "Godina izgradnje": "2023.",
  "Broj parkirnih mjesta": "3",
  "Balkon/Lođa/Terasa": "Balkon",
  "Šifra objekta": "300291007-230",
  "opis": "Moderna katnica u izgradnji veličine 182 m2 smještena je na samo par minuta vožnje od grada Labina. Kuća se sastoji od prizemlja u kojem se nalaze open space kuhinja s blagovaonom i dnevni boravak, WC i ostava te kata na kojem su tri spavaće soba svaka sa svojom kupaonicom i utility room. Dnevni boravak ima izlaz na natkrivenu terasu gdje je smještena ljetna kuhinja i dodatan WC koji će biti povezani sa bazenom 13 x 4,5 m2. Grijanje će biti podno putem dizalice topline a svaka soba imati će klima uređaj marke Daikin. Kuća je opremljena Smart Home sustavom za zaštitu, nadzor i jednostavnije upravljanje svojim domom. Planirani završetak izgradnje je 2024. godina a kuća se prodaje kompletno završena i namještena te sa uređenom okućnicom. ID KOD AGENCIJE: 300291007-230 ESTER  GERGORIĆ Agent Mob: 0997466050 Tel: +385 52 496 062 E-mail: e.gergoric@remax.hr www.remax-istra.com",
  "Podaci o objektu": [
    "Novogradnja"
  ],
  "Funkcionalnosti i ostale karakteristike": [
    "Protuprovalna vrata"
  ],
  "Kupaonica i WC": [
    "Broj kupaonica s WC-om: 3",
    "Broj WC-a: 2"
  ],
  "Ostali objekti i površine": [
    "Dvorište/vrt"
  ],
  "naziv_agencije": "RE/MAX PLUS Labin",
  "profil_agencije": "https://www.njuskalo.hr/agencija/remax-plus",
  "email_agencije": "erna.radicanin@gmail.com",
  "adresa_agencije": "Adresa:Zelenice 7, 52220 Labin, Istarska, Hrvatska",
  "telefon": "091 286 5688",
  "oglas_objavljen": "29.07.2025. u 10:26",
  "do_isteka": "do prodaje",
  "oglas_prikazan": "607 puta",
  "slike": [
    "https://www.njuskalo.hr/image-xlsize/nekretnine/istra-labin-moderna-novogradnja-bazenom-slika-246897662.jpg",
    "https://www.njuskalo.hr/image-xlsize/nekretnine/istra-labin-moderna-novogradnja-bazenom-slika-246897665.jpg",
    "https://www.njuskalo.hr/image-xlsize/nekretnine/istra-labin-moderna-novogradnja-bazenom-slika-246897677.jpg",
    "https://www.njuskalo.hr/image-xlsize/nekretnine/istra-labin-moderna-novogradnja-bazenom-slika-246897680.jpg",
    "https://www.njuskalo.hr/image-xlsize/nekretnine/istra-labin-moderna-novogradnja-bazenom-slika-246897685.jpg",
    "https://www.njuskalo.hr/image-xlsize/nekretnine/istra-labin-moderna-novogradnja-bazenom-slika-246897689.jpg",
    "https://www.njuskalo.hr/image-xlsize/nekretnine/istra-labin-moderna-novogradnja-bazenom-slika-246897693.jpg",
    "https://www.njuskalo.hr/image-xlsize/nekretnine/istra-labin-moderna-novogradnja-bazenom-slika-246897697.jpg"
  ]
}