{
  "id": "42136360",
  "link": "https://www.njuskalo.hr/nekretnine/otok-krk-soto-vento-kamnea-adaptirana-kuca-prodaju-oglas-42136360",
  "lokacija": {
    "lat": 45.087610314086,
    "lng": 14.46576586128,
    "approximate": true
  },
  "naslov": "OTOK KRK,ŠOTO VENTO kamena adaptirana kuća na prodaju (prodaja)",
  "cijena": "420.000 €",
  "Lokacija": "Primorsko-goranska, Krk, Milohnići",
  "Tip kuće": "U nizu",
  "Broj etaža": "Dvokatnica",
  "Broj soba": "8",
  "Stambena površina": "200,00 m²",
  "Površina okućnice": "100,00 m²",
  "Godina izgradnje": "1900.",
  "Balkon/Lođa/Terasa": "Balkon",
  "Šifra objekta": "300621003-1278",
  "opis": "Nudimo na prodaju predivnu kamenu adaptiranu kuću smještenu na području Šoto Venta, u samom centru mjesta. Kuća je koncipirana kao kuća u nizu na tri etaže - prizemlje, prvi i drugi kat, pružajući raznovrsne prostore. U prizemlju se nalazi odvojeno spremište, kao i zaseban apartman s kupaonicom, kuhinjom s blagovaonicom, dnevnim boravkom i spavaćom sobom. Prvi kat obuhvaća kupaonicu, kuhinju s blagovaonicom, dnevni boravak, spavaću sobu i prostranu terasu. Na drugom katu su planirane dvije spavaće sobe, kupaonica, kuhinja i još jedna terasa. Kuća je u potpunosti adaptirana 2023. godine, uključujući instalacije struje i vode, keramiku, sanitarije i zidove. Okućnica će biti uređena, pružajući mogućnost parkiranja dva automobila. Udaljenost do mora i plaže u Brzacu ili uvali Vela Jana iznosi 2500 metara. Za dodatne informacije ili razgledavanje, slobodno se obratite agentu Mireli Petrović na Krku putem telefona +385916413300 ili e-maila m.petrovic@remax-krk.hr. ID KOD AGENCIJE: 300621003-1278 Mirela Petrović Prodajni predstavnik Mob: +385 91 641 3300 Tel: +385 51 309 703 E-mail: m.petrovic@remax-krk.hr remax-centarnekretnina.com",
  "Grijanje": [
    "Klima uređaj: Da"
  ],
  "Kupaonica i WC": [
    "Broj kupaonica s WC-om: 3"
  ],
  "Ostali objekti i površine": [
    "Spremište/šupa"
  ],
  "naziv_agencije": "RE/MAX Centar nekretnina",
  "profil_agencije": "https://www.njuskalo.hr/agencija/remax-centarnekretnina",
  "email_agencije": "info@remax-centarnekretnina.hr",
  "adresa_agencije": "Adresa:Primorsko-goranska, Hrvatska",
  "telefon": "091 641 3300",
  "oglas_objavljen": "20.05.2025. u 16:03",
  "do_isteka": "do prodaje",
  "oglas_prikazan": "776 puta",
  "slike": [
    "https://www.njuskalo.hr/image-xlsize/nekretnine/otok-krk-soto-vento-kamnea-adaptirana-kuca-prodaju-slika-208295222.jpg",
    "https://www.njuskalo.hr/image-xlsize/nekretnine/otok-krk-soto-vento-kamnea-adaptirana-kuca-prodaju-slika-208295223.jpg"
  ]
}