{
  "id": "43160811",
  "link": "https://www.njuskalo.hr/nekretnine/mobilne-kuce-razni-modeli-oglas-43160811",
  "lokacija": {
    "lat": 46.250814,
    "lng": 16.14685,
    "approximate": false
  },
  "naslov": "Mobilne kuće razni modeli (prodaja)",
  "cijena": "45.000 €",
  "Lokacija": "Varaždinska, Maruševec, Druškovec",
  "Tip kuće": "Samostojeća",
  "Broj etaža": "Prizemnica",
  "Vrsta kuće (gradnje)": "Drvena kuća",
  "Broj soba": "3",
  "Stambena površina": "90,00 m²",
  "Godina izgradnje": "2024.",
  "Namještenost i stanje": "Potpuno namješteno",
  "Šifra objekta": "300541013-272",
  "opis": "Prodaju se gotovi tipski objekti- mobilne kuće. Može se birati između nekoliko modela različitih stilova i veličina. Svi objekti izrađuju se ručno, što svakom pojedinom modelu daje osobnost i pruža trajnost i kvalitetu. Mobilne kuće prodaju se po sistemu \"ključ u ruke\"-kompletno opremljene i namještene. Ponuda obuhvaća 7 vrsta mobilnih kuća: 1. \"BORNA\"- unutrašnjost 12 m2+ terasa 8 m2 =20 m2 - 11.750 eur (uključen PDV) 2. \"BRUNO\"-unutrašnjost 16 m2+ galerija 1,5 m2 + terasa 12 m2 = 29,5 m2 - 30.000 eur (uključen PDV) 3. \"BOJAN\"- unutrašnjost 24 m2 + galerija 9 m2 + terasa 11 m2 = 44 m2 - 45.000 eur (uključen PDV) 4. \"MARIN\" - unutrašnjost 24 m2 + galerija 9 m2 + terasa 11 m2 = 44 m2 - 45.000 eur (uključen PDV) 5. \"MIRJANA\" - unutrašnjost 24 m2 + galerija 9 m2 + terasa 11 m2 = 44 m2 - 45.000 eur (uključen PDV) 6. \"AURORA\" - unutrašnjost 32 m2 + terasa 22 m2 = 54 m2 - 68.750 eur (uključen PDV) 7. \"ADRIAN\" - unutrašnjost 46 m2 + terasa 28 m2 = 74 m2 - 85.000 eur (uključen PDV) Uz ove gotove verzije postoji i mogućnost izrade po mjeri. U navedene cijene uključeno je: dokumentacija uz objekt, stolarija, kompletan namještaj po mjeri, kuhinjski aparati, senzori, sanitarije, sustav za kontrolu grijanja i hlađenja,, instalacije, rasvjetna tijela,, obloge, betonski blokovi na koje se postavlja objekt, montaža i spajanje od strane proizvođača. Za dogovor oko razgledavanja i dodatne informacije kontakt: +385 42 456 662 ili +385 91 5511 785 - Ana",
  "Grijanje": [
    "Sustav grijanja: Nema sustav grijanja"
  ],
  "Kupaonica i WC": [
    "Broj kupaonica s WC-om: 1",
    "Broj WC-a: 1"
  ],
  "naziv_agencije": "RE/MAX City 1 Varaždin",
  "profil_agencije": "https://www.njuskalo.hr/agencija/remax-city1",
  "adresa_agencije": "Adresa:Varaždinska, Hrvatska",
  "telefon": "042 456 661",
  "oglas_objavljen": "19.05.2025. u 10:05",
  "do_isteka": "do prodaje",
  "oglas_prikazan": "7296 puta",
  "slike": [
    "https://www.njuskalo.hr/image-xlsize/nekretnine/mobilne-kuce-razni-modeli-slika-247522782.jpg",
    "https://www.njuskalo.hr/image-xlsize/nekretnine/mobilne-kuce-razni-modeli-slika-247522783.jpg",
    "https://www.njuskalo.hr/image-xlsize/nekretnine/mobilne-kuce-razni-modeli-slika-247522784.jpg",
    "https://www.njuskalo.hr/image-xlsize/nekretnine/mobilne-kuce-razni-modeli-slika-247522785.jpg",
    "https://www.njuskalo.hr/image-xlsize/nekretnine/mobilne-kuce-razni-modeli-slika-247522786.jpg",
    "https://www.njuskalo.hr/image-xlsize/nekretnine/mobilne-kuce-razni-modeli-slika-247522787.jpg",
    "https://www.njuskalo.hr/image-xlsize/nekretnine/mobilne-kuce-razni-modeli-slika-247522788.jpg",
    "https://www.njuskalo.hr/image-xlsize/nekretnine/mobilne-kuce-razni-modeli-slika-247522789.jpg",
    "https://www.njuskalo.hr/image-xlsize/nekretnine/mobilne-kuce-razni-modeli-slika-247522790.jpg",
    "https://www.njuskalo.hr/image-xlsize/nekretnine/mobilne-kuce-razni-modeli-slika-247522792.jpg",
    "https://www.njuskalo.hr/image-xlsize/nekretnine/mobilne-kuce-razni-modeli-slika-247522793.jpg",
    "https://www.njuskalo.hr/image-xlsize/nekretnine/mobilne-kuce-razni-modeli-slika-247522794.jpg",
    "https://www.njuskalo.hr/image-xlsize/nekretnine/mobilne-kuce-razni-modeli-slika-247522795.jpg",
    "https://www.njuskalo.hr/image-xlsize/nekretnine/mobilne-kuce-razni-modeli-slika-247522796.jpg",
    "https://www.njuskalo.hr/image-xlsize/nekretnine/mobilne-kuce-razni-modeli-slika-247522797.jpg"
  ]
}