{
  "id": "43404935",
  "link": "https://www.njuskalo.hr/nekretnine/grizane-kuca-vanjskim-grijanim-bazenom-oglas-43404935",
  "lokacija": {
    "lat": 45.235774780969,
    "lng": 14.757910840413,
    "approximate": true
  },
  "naslov": "GRIŽANE, KUĆA S GRIJANIM BAZENOM I OKUĆNICOM (prodaja)",
  "cijena": "350.000 €",
  "Lokacija": "Primorsko-goranska, Vinodolska Općina, Grižane-Belgrad",
  "Tip kuće": "Samostojeća",
  "Broj etaža": "Katnica",
  "Broj soba": "5",
  "Stambena površina": "152,00 m²",
  "Površina okućnice": "309,00 m²",
  "Godina izgradnje": "1982.",
  "Godina zadnje renovacije": "2022.",
  "Broj parkirnih mjesta": "2",
  "Balkon/Lođa/Terasa": "Terasa",
  "Pogled na more": "Da",
  "Energetski razred": "A",
  "Šifra objekta": "2489",
  "opis": "CRIKVENICA, GRIŽANE, u ponudi imamo samostojeću kuću s okućnicom, grijanim bazenom za uživanje u većem dijelu godine te pogledom na more. Sastoji se od prizemlja i kata povezanih unutarnjim stepenicama. Prizemlje čini hodnik, kuhinja s blagovaonicom, dnevni boravak, kupaonica i toalet, terasa, unutarnje stubište kojim se dolazi na prvi kat gdje su tri spavaće sobe, kupaonica i toalet te veliki balkon s prekrasnim pogledom na prirodu i more. Kuća je potpuno adaptirana 2022.: PVC stolarija, centralno grijanje na pelete, kamin na drva... U sklopu lijepo uređene okućnice površine 200m2, nalazi se bazen sa grijanom vodom koja se grije pomoću dizalice topline, ljetna kuhinja i prostor za druženje te roštilj. U dvorištu je i parkirni prostor za dva automobila. Zaleđe Crikvenice, od mora udaljeno 4 km, mirna lokacija, okružena prirodnim zelenilom, obogaćenog sadržaja za uživanje, spremna za korištenje. Odličan je odabir za cjelogodišnji obiteljski život ili investicija u turističke djelatnost. Kuća za odmor ili stanovanje. Grižane, mjesto u Vinodolu, u srednjem je vijeku jedan od gradova Vinodolske gospoštije. Posjed je krčkih knezova Frankopana od 1225. Prvi put spominje se 1288. u Vinodolskom zakonu. Crikvenica je tada bila grižanska luka. Kaštel Grižane imao je u povijesti središnju ulogu u zaštiti Vinodola. Sam naziv Grižane dolazi od riječi griža, što znači litica, jer je sam kaštel podignut na litici prirodno odvojenoj od planine. Ako se dolazi iz smjera Rijeke, treba voziti prema Crikvenici i Selcu, a nakon prolaska kroz mjesto Selce skrenuti na lokalnu cestu 5062, po kojoj se stiže u naselje Grižane. Za sve dodatne informacije obratite se s povjerenjem. Vesna Smolčić agent s licencom +385 91 571 7682 vesna@spatium.hr Mislav Smolčić asistent u posredovanju +385 91 500 6757 mislav@spatium.hr Spatium nekretnine +385 51 452 479 info@spatium.hr ID KOD AGENCIJE: 2489 Vesna Smolčić Agent s licencom Mob: +385 91 571 7682 Tel: +385 51 452 479 E-mail: vesna@spatium.hr www.spatium.hr Mislav Smolčić Asistent u posredovanju Mob: +385 91 500 6757 Tel: +385 51 452 479 E-mail: mislav@spatium.hr www.spatium.hr",
  "Grijanje": [
    "Sustav grijanja: Sustav grijanja, klimatizacije i ventilacije",
    "Klima uređaj: Da"
  ],
  "Podaci o objektu": [
    "Gradski vodovod"
  ],
  "Dozvole i potvrde": [
    "Građevinska dozvola",
    "Uporabna dozvola"
  ],
  "Kupaonica i WC": [
    "Broj kupaonica s WC-om: 2"
  ],
  "Ostali objekti i površine": [
    "Dvorište/vrt",
    "Roštilj",
    "Bazen"
  ],
  "naziv_agencije": "SPATIUM nekretnine",
  "profil_agencije": "https://www.njuskalo.hr/agencija/spatium-nekretnine",
  "adresa_agencije": "Adresa:Šetalište Andrije Kačića Miošića 5, 51000 Rijeka, Primorsko-goranska, Hrvatska",
  "telefon": "051 272 903",
  "oglas_objavljen": "18.07.2025. u 09:57",
  "do_isteka": "do prodaje",
  "oglas_prikazan": "1490 puta",
  "slike": [
    "https://www.njuskalo.hr/image-xlsize/nekretnine/grizane-kuca-vanjskim-grijanim-bazenom-slika-232123397.jpg",
    "https://www.njuskalo.hr/image-xlsize/nekretnine/grizane-kuca-vanjskim-grijanim-bazenom-slika-232123398.jpg",
    "https://www.njuskalo.hr/image-xlsize/nekretnine/grizane-kuca-vanjskim-grijanim-bazenom-slika-232123399.jpg",
    "https://www.njuskalo.hr/image-xlsize/nekretnine/grizane-kuca-vanjskim-grijanim-bazenom-slika-232123400.jpg",
    "https://www.njuskalo.hr/image-xlsize/nekretnine/grizane-kuca-vanjskim-grijanim-bazenom-slika-232123401.jpg",
    "https://www.njuskalo.hr/image-xlsize/nekretnine/grizane-kuca-vanjskim-grijanim-bazenom-slika-232123402.jpg",
    "https://www.njuskalo.hr/image-xlsize/nekretnine/grizane-kuca-vanjskim-grijanim-bazenom-slika-232123403.jpg",
    "https://www.njuskalo.hr/image-xlsize/nekretnine/grizane-kuca-vanjskim-grijanim-bazenom-slika-232123404.jpg",
    "https://www.njuskalo.hr/image-xlsize/nekretnine/grizane-kuca-vanjskim-grijanim-bazenom-slika-232123405.jpg",
    "https://www.njuskalo.hr/image-xlsize/nekretnine/grizane-kuca-vanjskim-grijanim-bazenom-slika-232123406.jpg",
    "https://www.njuskalo.hr/image-xlsize/nekretnine/grizane-kuca-vanjskim-grijanim-bazenom-slika-232123407.jpg",
    "https://www.njuskalo.hr/image-xlsize/nekretnine/grizane-kuca-vanjskim-grijanim-bazenom-slika-232123408.jpg",
    "https://www.njuskalo.hr/image-xlsize/nekretnine/grizane-kuca-vanjskim-grijanim-bazenom-slika-232123409.jpg",
    "https://www.njuskalo.hr/image-xlsize/nekretnine/grizane-kuca-vanjskim-grijanim-bazenom-slika-232123410.jpg",
    "https://www.njuskalo.hr/image-xlsize/nekretnine/grizane-kuca-vanjskim-grijanim-bazenom-slika-232123411.jpg",
    "https://www.njuskalo.hr/image-xlsize/nekretnine/grizane-kuca-vanjskim-grijanim-bazenom-slika-232123412.jpg",
    "https://www.njuskalo.hr/image-xlsize/nekretnine/grizane-kuca-vanjskim-grijanim-bazenom-slika-232123413.jpg",
    "https://www.njuskalo.hr/image-xlsize/nekretnine/grizane-kuca-vanjskim-grijanim-bazenom-slika-232123414.jpg",
    "https://www.njuskalo.hr/image-xlsize/nekretnine/grizane-kuca-vanjskim-grijanim-bazenom-slika-232123415.jpg",
    "https://www.njuskalo.hr/image-xlsize/nekretnine/grizane-kuca-vanjskim-grijanim-bazenom-slika-232123416.jpg",
    "https://www.njuskalo.hr/image-xlsize/nekretnine/grizane-kuca-vanjskim-grijanim-bazenom-slika-232123417.jpg",
    "https://www.njuskalo.hr/image-xlsize/nekretnine/grizane-kuca-vanjskim-grijanim-bazenom-slika-232123418.jpg",
    "https://www.njuskalo.hr/image-xlsize/nekretnine/grizane-kuca-vanjskim-grijanim-bazenom-slika-232123419.jpg",
    "https://www.njuskalo.hr/image-xlsize/nekretnine/grizane-kuca-vanjskim-grijanim-bazenom-slika-232123420.jpg"
  ]
}