{
  "id": "44322437",
  "link": "https://www.njuskalo.hr/nekretnine/prekrasna-kuca-prvi-red-mora-oglas-44322437",
  "lokacija": {
    "lat": 43.497818043853854,
    "lng": 16.33236267631058,
    "approximate": true
  },
  "naslov": "Prekrasna kuća prvi red od mora. PRILIKA ! (prodaja)",
  "cijena": "1.200.000 €",
  "Lokacija": "Splitsko-dalmatinska, Split - Okolica, Slatine",
  "Tip kuće": "Samostojeća",
  "Broj etaža": "Dvokatnica",
  "Vrsta kuće (gradnje)": "Kamena kuća",
  "Broj soba": "6",
  "Stambena površina": "200,00 m²",
  "Površina okućnice": "800,00 m²",
  "Namještenost i stanje": "Potpuno namješteno",
  "Broj parkirnih mjesta": "4",
  "Balkon/Lođa/Terasa": "Balkon, Terasa",
  "Pogled na more": "Da",
  "Šifra objekta": "617",
  "Razgledavanje putem video poziva": "Da",
  "opis": "Kuća je prvi red uz more s izlazom na plažu (bez ceste između, direktan izlaz na plažu). Kuća originalno ima 200m2 a u međuvremenu je zatvorena stara terasa i dograđena nova terasa čime je kuća dobila još 60m2 (jedna prostorija na katu i jedna u prizemlju po 30m2) unutrašnjeg prostora i trenutno stvarno stanje iznosi 260m2 (bez niskog potkrovlja). Terase su veličina 30m2 na drugom katu i 70m2 na prvom. Za ovo proširenje od nije tražena dozvola ali se može lako ishoditi jer se nalazi na građevnom dijelu čestice. Kuća je na velikom zemljištu od skoro 800m2 a proteže se na tri etaže + nisko potkrovlje: – U prizemlju se nalazi garaža od cca 80m2, gdje dio prostora služi kao ostava. Na ovoj etaži ima i dodatna prostorija s pogledom na more, nekad ljetna kuhinja a danas prostor pretvoren u mini teretanu odnosno prostor za rekreaciju i zabavu. – Na prvom katu smješten je komforni dnevni prostor, kuhinja i blagovaonica te izlaz na veliku terasu sa sjenicom i kaminom te s pogledom na more. Tu su još mala ostava, dvije sobe i dvije kupaonice. – Na drugom katu do kojeg se dolazi unutarnjim stepeništem nalaze se dodatne četiri sobe od kojih su tri s pogledom na more i dvije kupaonice. – Nisko potkrovlje nije povezano stubištem i ima vanjski ulaz. Po želji se može ishoditi proširenje građevinske dozvole  a kuća se može proširiti kako u visinu( nisko potkrovlje može se povisiti i povezati unutarnjim stepeništem) tako i u širinu. Kuća ima dvostruku prelivnu, 12m3, septičku jamu po građevinskoj i uporabnoj dozvoli, uz cestu. Ima još dvije manje u dvorištu, jedna samo za sivu vodu iz kuhinje a druga za planirani a neizgrađeni vanjski wc. Kuća će uskoro dobiti i gradsku kanalizaciju za koju postoje ucrtani planovi i ishodovane dozvole. Dvorište kuće njena je najveća vrijednost, veliko i komforno, pravilnog oblika, proteže se sve do plaže s direktnim izlazom na nju. U dvorištu se trenutno nalazi bazen s sunčalištem, jacuzzi, prostor za djecu, mali nogomet i ostali sadržaji. Pored garaže pogodne za jedno vozilo, nekretnina ima i 3 parking mjesta uz cestu te još 4 u dvorištu. Blizina svih sadržaja, autoceste, zračne luke i većih dalmatinskih središta. Mogućnost dogovora, za nekretninu u Splitu i okolici ili Zagrebu do 300.000 eura, pod račun. Za razgledavanje ovog objekta nazovite: +385989322461 (Whats up/ Viber) Vlasnik agencije Mario Marević Agencija Get Home Šifra objekta: 617",
  "Podaci o objektu": [
    "Pristup za osobe s invaliditetom",
    "Gradski vodovod",
    "Gradska kanalizacija"
  ],
  "Dozvole i potvrde": [
    "Vlasnički list",
    "Građevinska dozvola",
    "Uporabna dozvola"
  ],
  "Vrsta parkinga": [
    "Garaža",
    "Vanjsko ne-natkriveno mjesto"
  ],
  "Funkcionalnosti i ostale karakteristike": [
    "Protuprovalna vrata",
    "Alarmni sustav",
    "Video Portafon",
    "Kada",
    "Tuš kabina",
    "Jacuzzi",
    "Podno grijanje",
    "Kamin",
    "Sauna",
    "Električne rolete",
    "Perilica posuđa"
  ],
  "Ostali objekti i površine": [
    "Dvorište/vrt",
    "Podrum",
    "Spremište/šupa",
    "Roštilj",
    "Zimski vrt",
    "Bazen",
    "Vrtna kućica"
  ],
  "naziv_agencije": "Get Home",
  "profil_agencije": "https://www.njuskalo.hr/agencija/gethome",
  "adresa_agencije": "Adresa:Splitsko-dalmatinska, Hrvatska",
  "telefon": "098 932 2461",
  "oglas_objavljen": "29.07.2025. u 17:12",
  "do_isteka": "do prodaje",
  "oglas_prikazan": "883 puta",
  "slike": [
    "https://www.njuskalo.hr/image-xlsize/nekretnine/prekrasna-kuca-prvi-red-mora-slika-224318814.jpg",
    "https://www.njuskalo.hr/image-xlsize/nekretnine/prekrasna-kuca-prvi-red-mora-slika-224318815.jpg",
    "https://www.njuskalo.hr/image-xlsize/nekretnine/prekrasna-kuca-prvi-red-mora-slika-224318816.jpg",
    "https://www.njuskalo.hr/image-xlsize/nekretnine/prekrasna-kuca-prvi-red-mora-slika-224318817.jpg",
    "https://www.njuskalo.hr/image-xlsize/nekretnine/prekrasna-kuca-prvi-red-mora-slika-224318818.jpg",
    "https://www.njuskalo.hr/image-xlsize/nekretnine/prekrasna-kuca-prvi-red-mora-slika-224318819.jpg",
    "https://www.njuskalo.hr/image-xlsize/nekretnine/prekrasna-kuca-prvi-red-mora-slika-224318820.jpg",
    "https://www.njuskalo.hr/image-xlsize/nekretnine/prekrasna-kuca-prvi-red-mora-slika-224318821.jpg",
    "https://www.njuskalo.hr/image-xlsize/nekretnine/prekrasna-kuca-prvi-red-mora-slika-224318822.jpg",
    "https://www.njuskalo.hr/image-xlsize/nekretnine/prekrasna-kuca-prvi-red-mora-slika-224318823.jpg",
    "https://www.njuskalo.hr/image-xlsize/nekretnine/prekrasna-kuca-prvi-red-mora-slika-224318824.jpg",
    "https://www.njuskalo.hr/image-xlsize/nekretnine/prekrasna-kuca-prvi-red-mora-slika-224318825.jpg"
  ]
}