{
  "id": "44414255",
  "link": "https://www.njuskalo.hr/nekretnine/korcula-centar-prodaja-kuca-terasa-pogled-more-oglas-44414255",
  "lokacija": {
    "lat": 42.961073682636,
    "lng": 17.135797310065,
    "approximate": false
  },
  "naslov": "Korčula, centar, prodaja kuća, terasa, pogled na more (prodaja)",
  "cijena": "700.000 €",
  "Lokacija": "Dubrovačko-neretvanska, Korčula, Korčula",
  "Tip kuće": "U nizu",
  "Broj etaža": "Dvokatnica",
  "Broj soba": "5",
  "Stambena površina": "200,00 m²",
  "Netto površina": "200,00 m²",
  "Godina izgradnje": "1989.",
  "Balkon/Lođa/Terasa": "Terasa",
  "Pogled na more": "Da",
  "Šifra objekta": "14436",
  "Mogućnost zamjene": "Nije moguća zamjena za drugu nekretninu",
  "opis": "Korčula, Stari Grad, kamena kuća u nizu na 4 etaže, tlocrtne površine 54m2. Kuća je izgrađena 1989.,a useljena je 1994. Lokacija kuće je vrlo zanimljiva, nalazi se u samoj staroj jezgri, u neposrednoj blizini kuće Marka Pola. Rijetko se uopće može naći nešto u ponudi na ovoj loakciji. U prizemlju se nalazi studio apartman s posebnim ulazom, kuhinja i WC koji su unutarnjim stepeništem povezani sa ostalim etažama. Na prvom katu su 2 sobe i 2 kupaonice. Na drugom katu su dvije sobe i jedna kupaonica. Na 3.katu; potkrovlje, nalazi se terasa, a stambeni dio nije uređen. S terase se pruža pogled na more i Pelješac. Kuća je održavana i useljiva. www.biliskov.com    ID:14436-1",
  "Grijanje": [
    "Sustav grijanja: Grijalice i radijatori na struju",
    "Dodatni izvor grijanja: Da",
    "Klima uređaj: Da"
  ],
  "Podaci o objektu": [
    "Gradska kanalizacija",
    "Gradski vodovod"
  ],
  "Dozvole i potvrde": [
    "Građevinska dozvola"
  ],
  "Kupaonica i WC": [
    "Broj kupaonica s WC-om: 4",
    "Broj WC-a: 1"
  ],
  "naziv_agencije": "Biliškov nekretnine d.o.o.",
  "profil_agencije": "https://www.njuskalo.hr/agencija/biliskov-nekretnine",
  "email_agencije": "info@biliskov.com",
  "adresa_agencije": "Adresa:Splitsko-dalmatinska, Hrvatska",
  "telefon": "01 3011 383",
  "oglas_objavljen": "31.07.2025. u 14:44",
  "do_isteka": "do prodaje",
  "oglas_prikazan": "1119 puta",
  "slike": [
    "https://www.njuskalo.hr/image-xlsize/nekretnine/korcula-centar-prodaja-kuca-terasa-pogled-more-slika-252191970.jpg",
    "https://www.njuskalo.hr/image-xlsize/nekretnine/korcula-centar-prodaja-kuca-terasa-pogled-more-slika-252191972.jpg",
    "https://www.njuskalo.hr/image-xlsize/nekretnine/korcula-centar-prodaja-kuca-terasa-pogled-more-slika-252191974.jpg",
    "https://www.njuskalo.hr/image-xlsize/nekretnine/korcula-centar-prodaja-kuca-terasa-pogled-more-slika-252191978.jpg",
    "https://www.njuskalo.hr/image-xlsize/nekretnine/korcula-centar-prodaja-kuca-terasa-pogled-more-slika-252191983.jpg",
    "https://www.njuskalo.hr/image-xlsize/nekretnine/korcula-centar-prodaja-kuca-terasa-pogled-more-slika-252191987.jpg",
    "https://www.njuskalo.hr/image-xlsize/nekretnine/korcula-centar-prodaja-kuca-terasa-pogled-more-slika-252191990.jpg",
    "https://www.njuskalo.hr/image-xlsize/nekretnine/korcula-centar-prodaja-kuca-terasa-pogled-more-slika-252191993.jpg",
    "https://www.njuskalo.hr/image-xlsize/nekretnine/korcula-centar-prodaja-kuca-terasa-pogled-more-slika-252191995.jpg"
  ]
}