{
  "id": "44852080",
  "link": "https://www.njuskalo.hr/nekretnine/kuca-potencijalom-adaptaciju-grizane-oglas-44852080",
  "lokacija": {
    "lat": 45.236842037653,
    "lng": 14.755118340061,
    "approximate": true
  },
  "naslov": "PRILIKA!! Kuća sa potencijalom za adaptaciju Grižane (prodaja)",
  "cijena": "85.000 €",
  "Lokacija": "Primorsko-goranska, Vinodolska Općina, Grižane-Belgrad",
  "Tip kuće": "Samostojeća",
  "Broj etaža": "Katnica",
  "Broj soba": "5",
  "Stambena površina": "130,00 m²",
  "Površina okućnice": "300,00 m²",
  "Godina izgradnje": "1968.",
  "Godina zadnje renovacije": "1998.",
  "Broj parkirnih mjesta": "3",
  "Balkon/Lođa/Terasa": "Balkon, Lođa (Loggia), Terasa",
  "Šifra objekta": "16235",
  "opis": "PRILIKA!!! Starina za adaptaciju u okolici centra Grižana Na prodaju je starina s izuzetnim potencijalom, smještena u blizini centra Grižana i okružena prekrasnim vilama i adaptiranim starinama. Ova nekretnina sastoji se od prizemlja i prvog kata, s dodatnim prostorom u obliku ostave, odvojene konobe i ljetne kuhinje unutar ograđenog dijela dvorišta. Nekretnini pripada i prostrani vrt koji nudi brojne mogućnosti, savršen za izgradnju garaže, bazena ili sunčališta, stvarajući prostor za uživanje na otvorenom. Ova kuća pruža ogromnu priliku za adaptaciju i ulaganje, uz potencijal za generiranje prihoda do 50.000 EUR kroz iznajmljivanje. Mjesto je izuzetno mirno, idealno za ljubitelje tišine i prirode, a opet blizu svih potrebnih sadržaja. Lokacija je svega nekoliko minuta vožnje od centra Crikvenice, osiguravajući lakoću pristupa svim važnim mestima. Ne propustite ovu rijetku priliku da postanete vlasnik nekretnine s velikim potencijalom po povoljnoj cijeni. Donosite odluku koja može dovesti do ostvarenja vaših snova o savršenom obiteljskom domu ili investiciji! ZA SVA PITANJA KAO I OGLED NEKRETNINE OBRATITE SE: ROBERTO-BRUNO REŠETAR GSM: +385998486365 Mail: bruno.resetar@dogma-nekretnine.com ID KOD AGENCIJE: 16235 Roberto-Bruno Rešetar Asistent u posredovanju Mob: 099/848-6365 Tel: 051 348 508 E-mail: bruno.resetar@dogma-nekretnine.com www.dogma-nekretnine.com",
  "Podaci o objektu": [
    "Gradski vodovod"
  ],
  "Dozvole i potvrde": [
    "Vlasnički list",
    "Uporabna dozvola"
  ],
  "Funkcionalnosti i ostale karakteristike": [
    "Kamin"
  ],
  "Kupaonica i WC": [
    "Broj kupaonica s WC-om: 2"
  ],
  "Ostali objekti i površine": [
    "Dvorište/vrt",
    "Podrum",
    "Spremište/šupa",
    "Roštilj",
    "Vrtna kućica"
  ],
  "naziv_agencije": "Dogma nekretnine",
  "profil_agencije": "https://www.njuskalo.hr/agencija/dogma-nekretnine",
  "email_agencije": "info@dogma-nekretnine.com",
  "adresa_agencije": "Adresa:Primorsko-goranska, Hrvatska",
  "telefon": null,
  "oglas_objavljen": "23.07.2025. u 12:37",
  "do_isteka": "do prodaje",
  "oglas_prikazan": "15403 puta",
  "slike": [
    "https://www.njuskalo.hr/image-xlsize/nekretnine/kuca-potencijalom-adaptaciju-grizane-slika-252870628.jpg",
    "https://www.njuskalo.hr/image-xlsize/nekretnine/kuca-potencijalom-adaptaciju-grizane-slika-252870629.jpg",
    "https://www.njuskalo.hr/image-xlsize/nekretnine/kuca-potencijalom-adaptaciju-grizane-slika-252870630.jpg",
    "https://www.njuskalo.hr/image-xlsize/nekretnine/kuca-potencijalom-adaptaciju-grizane-slika-252870631.jpg",
    "https://www.njuskalo.hr/image-xlsize/nekretnine/kuca-potencijalom-adaptaciju-grizane-slika-252870632.jpg",
    "https://www.njuskalo.hr/image-xlsize/nekretnine/kuca-potencijalom-adaptaciju-grizane-slika-252870633.jpg",
    "https://www.njuskalo.hr/image-xlsize/nekretnine/kuca-potencijalom-adaptaciju-grizane-slika-252870634.jpg",
    "https://www.njuskalo.hr/image-xlsize/nekretnine/kuca-potencijalom-adaptaciju-grizane-slika-252870635.jpg",
    "https://www.njuskalo.hr/image-xlsize/nekretnine/kuca-potencijalom-adaptaciju-grizane-slika-252870636.jpg",
    "https://www.njuskalo.hr/image-xlsize/nekretnine/kuca-potencijalom-adaptaciju-grizane-slika-252870637.jpg",
    "https://www.njuskalo.hr/image-xlsize/nekretnine/kuca-potencijalom-adaptaciju-grizane-slika-252870638.jpg",
    "https://www.njuskalo.hr/image-xlsize/nekretnine/kuca-potencijalom-adaptaciju-grizane-slika-252870639.jpg",
    "https://www.njuskalo.hr/image-xlsize/nekretnine/kuca-potencijalom-adaptaciju-grizane-slika-252870640.jpg"
  ]
}