{
  "id": "44898632",
  "link": "https://www.njuskalo.hr/nekretnine/kuca-kastel-kambelovac-280.00-m2-oglas-44898632",
  "lokacija": {
    "lat": 43.54902451923,
    "lng": 16.385801254965,
    "approximate": true
  },
  "naslov": "Kuća: Kaštel Kambelovac, 280.00 m2 (prodaja)",
  "cijena": "440.000 €",
  "Lokacija": "Splitsko-dalmatinska, Kaštela, Kaštel Kambelovac",
  "Tip kuće": "Dvojna (duplex)",
  "Broj etaža": "Dvokatnica",
  "Vrsta kuće (gradnje)": "Zidana kuća (beton, opeka)",
  "Broj soba": "6",
  "Stambena površina": "280,00 m²",
  "Površina okućnice": "155,00 m²",
  "Godina zadnje renovacije": "2016.",
  "Namještenost i stanje": "Djelomično namješteno",
  "Broj parkirnih mjesta": "2",
  "Balkon/Lođa/Terasa": "Balkon",
  "Pogled na more": "Da",
  "Mogućnost zamjene": "Nije moguća zamjena za drugu nekretninu",
  "Agencijsku proviziju plaća": "Prodavatelj",
  "opis": "Prodaje se obiteljska kuća u Kaštel Kambelovcu. Kuća ima 2 stana sa zasebnim ulazom (zajedničko stubište) smještene na prvom i drugom katu, površine 90 kvadrata. U prizemlju je garaža sa skladišnim prostorijama koje se mogu pretvoriti u još jedan stan (svaka prostorija ima prozore). Potkrovlje kuće također je moguće adaptirati u životni prostor (ima propisanu visinu). Svi papiri uredni (vlasnički list, građevinska i uporabna dozvola, energetski certifikat). Mirna ulica bez prometa. Udaljenost do rive i mora - 300m Udaljenost do trgovine (supermarket, mesnica) - 200m Udaljenost do stanice javnog prijevoza - 200m Nema agencijske provizije, prodaje vlasnik direktno. Dodatne informacije moguće dobiti na 091/7619655",
  "Grijanje": [
    "Klima uređaj: Da"
  ],
  "Podaci o objektu": [
    "Gradski vodovod",
    "Gradska kanalizacija"
  ],
  "Dozvole i potvrde": [
    "Vlasnički list",
    "Građevinska dozvola",
    "Uporabna dozvola"
  ],
  "Vrsta parkinga": [
    "Garaža",
    "Garažno mjesto",
    "Vanjsko ne-natkriveno mjesto"
  ],
  "Kupaonica i WC": [
    "Broj kupaonica s WC-om: 2"
  ],
  "Ostali objekti i površine": [
    "Dvorište/vrt",
    "Podrum",
    "Spremište/šupa"
  ],
  "naziv_agencije": "mvasilj93",
  "profil_agencije": "https://www.njuskalo.hr/korisnik/mvasilj93",
  "adresa_agencije": "Adresa:Splitsko-dalmatinska, Hrvatska",
  "telefon": "091 761 9655",
  "oglas_objavljen": "19.03.2025. u 12:38",
  "oglas_prikazan": "1578 puta",
  "slike": [
    "https://www.njuskalo.hr/image-xlsize/nekretnine/kuca-kastel-kambelovac-280.00-m2-slika-228841388.jpg",
    "https://www.njuskalo.hr/image-xlsize/nekretnine/kuca-kastel-kambelovac-280.00-m2-slika-228841389.jpg",
    "https://www.njuskalo.hr/image-xlsize/nekretnine/kuca-kastel-kambelovac-280.00-m2-slika-228841595.jpg"
  ]
}