{
  "id": "46359219",
  "link": "https://www.njuskalo.hr/nekretnine/dvoetazna-kuca-medulinu-ulica-centar-oglas-46359219",
  "lokacija": {
    "lat": 44.82158035948534,
    "lng": 13.934938497473594,
    "approximate": true
  },
  "naslov": "DVOETAŽNA KUĆA U MEDULINU, ULICA CENTAR, MOGUĆA ZAMJENA (prodaja)",
  "cijena": "135.000 €",
  "Lokacija": "Istarska, Medulin, Medulin",
  "Tip kuće": "U nizu",
  "Broj etaža": "Katnica",
  "Vrsta kuće (gradnje)": "Kamena kuća",
  "Broj soba": "2",
  "Stambena površina": "45,00 m²",
  "opis": "Prodajem manju kamenu kuću u Medulinu koja se sastoji od prizemlja i tu je kuhinja sa blagovaonicom, kupaonica i stepenice za kat. Na katu je hodnik i jedna soba. Kuća je upisana sa 26 m2, ali je dvoetažna što znači da je kat tj u potkrovllj uređeno i sličnu kvadraturu kao i prizemlje. Na krovu je crijep.  Fasada je izolirana (stiropor 5 cm). Solarija drvena, protuprovalna ulazna vrata. Dvije klime. Grijanje na struju. Nalazi se 150 m udaljena od rive i glavne šetnice i plaže. Idealno za turizam i rentanje. Blizina ljekarne, trgovina ... Nekretnina se prodaje isključivo za gotovinu. Cijena nije fiksna!! Mogućnost zamjene za nekretninu u Dugom Selu, ili širi centar Zagreba ili Črnomerec, Dubrava...blizina tramvajske pruge. Detalji u direktnom kantaktu. Pogledati možete uvijek po dogovoru na 091 95 95 971",
  "Grijanje": [
    "Sustav grijanja: Grijalice i radijatori na struju",
    "Klima uređaj: Da"
  ],
  "Podaci o objektu": [
    "Gradski vodovod",
    "Gradska kanalizacija"
  ],
  "Dozvole i potvrde": [
    "Vlasnički list"
  ],
  "Kupaonica i WC": [
    "Broj kupaonica s WC-om: 1"
  ],
  "naziv_agencije": "Olga nekretnine",
  "profil_agencije": "https://www.njuskalo.hr/agencija/olga-nekretnine-osijek",
  "email_agencije": "olga@olga-nekretnine.com",
  "adresa_agencije": "Adresa:Kapucinska 17, 31000 Osijek, Osječko-baranjska, Hrvatska",
  "telefon": "091 959 5971",
  "oglas_objavljen": "07.07.2025. u 11:19",
  "do_isteka": "do prodaje",
  "oglas_prikazan": "1906 puta",
  "slike": [
    "https://www.njuskalo.hr/image-xlsize/nekretnine/dvoetazna-kuca-medulinu-ulica-centar-slika-242358494.jpg",
    "https://www.njuskalo.hr/image-xlsize/nekretnine/dvoetazna-kuca-medulinu-ulica-centar-slika-242358496.jpg",
    "https://www.njuskalo.hr/image-xlsize/nekretnine/dvoetazna-kuca-medulinu-ulica-centar-slika-242358498.jpg",
    "https://www.njuskalo.hr/image-xlsize/nekretnine/dvoetazna-kuca-medulinu-ulica-centar-slika-242358501.jpg",
    "https://www.njuskalo.hr/image-xlsize/nekretnine/dvoetazna-kuca-medulinu-ulica-centar-slika-242358503.jpg",
    "https://www.njuskalo.hr/image-xlsize/nekretnine/dvoetazna-kuca-medulinu-ulica-centar-slika-242358506.jpg",
    "https://www.njuskalo.hr/image-xlsize/nekretnine/dvoetazna-kuca-medulinu-ulica-centar-slika-242358508.jpg",
    "https://www.njuskalo.hr/image-xlsize/nekretnine/dvoetazna-kuca-medulinu-ulica-centar-slika-242358510.jpg"
  ]
}