{
  "id": "46476524",
  "link": "https://www.njuskalo.hr/nekretnine/kuca-zagreb-crnomerec-vinogradska-ulica-500.00-m2-oglas-46476524",
  "lokacija": {
    "lat": 45.82173184620561,
    "lng": 15.9510448331838,
    "approximate": false
  },
  "naslov": "Kuća: Zagreb (Črnomerec), Vinogradska ulica,500.00 m2 (prodaja)",
  "cijena": "750.000 €",
  "Lokacija": "Grad Zagreb, Črnomerec, Črnomerec",
  "Tip kuće": "Samostojeća",
  "Broj etaža": "Višekatnica",
  "Vrsta kuće (gradnje)": "Zidana kuća (beton, opeka)",
  "Broj soba": "10",
  "Stambena površina": "500,00 m²",
  "Netto površina": "500,00 m²",
  "Površina okućnice": "700,00 m²",
  "Godina izgradnje": "1990.",
  "Namještenost i stanje": "Potpuno namješteno",
  "Broj parkirnih mjesta": "5",
  "Balkon/Lođa/Terasa": "Balkon, Terasa",
  "opis": "Slobodan sam Vam ponuditi višekatnu obiteljsku kuću u elitnom dijelu Zagreba,Vinogradska ulica,opčina Črnomerec.Vlasnici su kuću gradili vrlo kvalitetno za sebe.Velićina parcele je cca 700 m2.Kuća je ukupne površine cca 500 m2 sa više stambenih jedinica koje su povezane stepenicama (predviđena ugradnja lifta ) i hodnicima.Kuća ima kotlovnicu i radijatore te klima uređaje.Mogućnost dodatnih stambenih jedinica u potkrovlju.U dvorištu je sagrađena mala kuća 11 m2 u kojoj je roštilj sa ražnjem predviđena za zabave.Sa ulične strane zgrade postoji garaža za 3-4 automobila ovisno o veličini te parking u dvorištu za 1-2 automobila. Uz stepenice na prvu etažu predviđena je i izgradnja lifta. U kući u zadnje vrijeme ne živi nitko i zato se prodaje. Zanimljiva za stanovanje,poslovni prostor,kiliniku,smještaj stranih radnika,stanovanje,dom za straije i nemoćne itd. Cijena za razgovor: 690.000,00 eur. Vlasništvo 1/1. U slučaju interesa slobodno me kontaktirajte. Mob: 0915777644",
  "Grijanje": [
    "Sustav grijanja: Etažno plinsko centralno",
    "Klima uređaj: Da"
  ],
  "Podaci o objektu": [
    "Gradski plin",
    "Gradski vodovod",
    "Gradska kanalizacija"
  ],
  "Dozvole i potvrde": [
    "Vlasnički list",
    "Građevinska dozvola",
    "Uporabna dozvola"
  ],
  "Vrsta parkinga": [
    "Garaža",
    "Vanjsko ne-natkriveno mjesto"
  ],
  "Funkcionalnosti i ostale karakteristike": [
    "Kada",
    "Tuš kabina",
    "Jacuzzi",
    "Perilica posuđa"
  ],
  "Kupaonica i WC": [
    "Broj kupaonica s WC-om: 3",
    "Broj WC-a: 2"
  ],
  "Ostali objekti i površine": [
    "Dvorište/vrt",
    "Spremište/šupa",
    "Roštilj",
    "Vrtna kućica"
  ],
  "naziv_agencije": "rasafarma",
  "profil_agencije": "https://www.njuskalo.hr/korisnik/rasafarma",
  "adresa_agencije": "Adresa:10000 Zagreb, Grad Zagreb, Hrvatska",
  "telefon": "091 577 7644",
  "oglas_objavljen": "24.07.2025. u 09:54",
  "oglas_prikazan": "1819 puta",
  "slike": [
    "https://www.njuskalo.hr/image-xlsize/nekretnine/kuca-zagreb-crnomerec-vinogradska-ulica-500.00-m2-slika-243650151.jpg",
    "https://www.njuskalo.hr/image-xlsize/nekretnine/kuca-zagreb-crnomerec-vinogradska-ulica-500.00-m2-slika-243650152.jpg",
    "https://www.njuskalo.hr/image-xlsize/nekretnine/kuca-zagreb-crnomerec-vinogradska-ulica-500.00-m2-slika-243650154.jpg",
    "https://www.njuskalo.hr/image-xlsize/nekretnine/kuca-zagreb-crnomerec-vinogradska-ulica-500.00-m2-slika-243650155.jpg",
    "https://www.njuskalo.hr/image-xlsize/nekretnine/kuca-zagreb-crnomerec-vinogradska-ulica-500.00-m2-slika-243650156.jpg",
    "https://www.njuskalo.hr/image-xlsize/nekretnine/kuca-zagreb-crnomerec-vinogradska-ulica-500.00-m2-slika-243650157.jpg",
    "https://www.njuskalo.hr/image-xlsize/nekretnine/kuca-zagreb-crnomerec-vinogradska-ulica-500.00-m2-slika-243650158.jpg",
    "https://www.njuskalo.hr/image-xlsize/nekretnine/kuca-zagreb-crnomerec-vinogradska-ulica-500.00-m2-slika-243650159.jpg",
    "https://www.njuskalo.hr/image-xlsize/nekretnine/kuca-zagreb-crnomerec-vinogradska-ulica-500.00-m2-slika-243650160.jpg",
    "https://www.njuskalo.hr/image-xlsize/nekretnine/kuca-zagreb-crnomerec-vinogradska-ulica-500.00-m2-slika-243650161.jpg",
    "https://www.njuskalo.hr/image-xlsize/nekretnine/kuca-zagreb-crnomerec-vinogradska-ulica-500.00-m2-slika-243650162.jpg",
    "https://www.njuskalo.hr/image-xlsize/nekretnine/kuca-zagreb-crnomerec-vinogradska-ulica-500.00-m2-slika-243650163.jpg",
    "https://www.njuskalo.hr/image-xlsize/nekretnine/kuca-zagreb-crnomerec-vinogradska-ulica-500.00-m2-slika-243650164.jpg",
    "https://www.njuskalo.hr/image-xlsize/nekretnine/kuca-zagreb-crnomerec-vinogradska-ulica-500.00-m2-slika-243650165.jpg",
    "https://www.njuskalo.hr/image-xlsize/nekretnine/kuca-zagreb-crnomerec-vinogradska-ulica-500.00-m2-slika-243650166.jpg"
  ]
}