{
  "id": "46959007",
  "link": "https://www.njuskalo.hr/nekretnine/kuca-zagreb-planina-donja-90.00-m2-oglas-46959007",
  "lokacija": {
    "lat": 45.92415481430215,
    "lng": 16.094166040420532,
    "approximate": false
  },
  "naslov": "Kuća: Zagreb (Planina Donja), 90.00 m2 (prodaja)",
  "cijena": "27.000 €",
  "Lokacija": "Grad Zagreb, Sesvete, Planina Donja",
  "Tip kuće": "Samostojeća",
  "Broj etaža": "Visoka prizemnica",
  "Broj soba": "3",
  "Stambena površina": "90,00 m²",
  "Godina izgradnje": "1934.",
  "Godina zadnje renovacije": "1985.",
  "Namještenost i stanje": "Djelomično namješteno",
  "opis": "Stara seoska kuca,do prije 4 godine se stanovalo u njoj.kuća ima priključak vode,struje i kanalizacije Kuca je drvene građe i zidana Papiri svi uredni Za sve info molim nazvati na broj 0915377877",
  "Grijanje": [
    "Sustav grijanja: Peć na drva"
  ],
  "Dozvole i potvrde": [
    "Vlasnički list",
    "Građevinska dozvola",
    "Uporabna dozvola"
  ],
  "Kupaonica i WC": [
    "Broj kupaonica s WC-om: 1"
  ],
  "Ostali objekti i površine": [
    "Podrum",
    "Spremište/šupa"
  ],
  "naziv_agencije": "Planina11",
  "profil_agencije": "https://www.njuskalo.hr/korisnik/Planina11",
  "adresa_agencije": "Adresa:Grad Zagreb, Hrvatska",
  "telefon": "091 537 7877",
  "oglas_objavljen": "05.05.2025. u 08:04",
  "oglas_prikazan": "7916 puta",
  "slike": [
    "https://www.njuskalo.hr/image-xlsize/nekretnine/kuca-zagreb-planina-donja-90.00-m2-slika-248570263.jpg",
    "https://www.njuskalo.hr/image-xlsize/nekretnine/kuca-zagreb-planina-donja-90.00-m2-slika-248570264.jpg",
    "https://www.njuskalo.hr/image-xlsize/nekretnine/kuca-zagreb-planina-donja-90.00-m2-slika-248570265.jpg",
    "https://www.njuskalo.hr/image-xlsize/nekretnine/kuca-zagreb-planina-donja-90.00-m2-slika-248570266.jpg",
    "https://www.njuskalo.hr/image-xlsize/nekretnine/kuca-zagreb-planina-donja-90.00-m2-slika-248570268.jpg",
    "https://www.njuskalo.hr/image-xlsize/nekretnine/kuca-zagreb-planina-donja-90.00-m2-slika-248570270.jpg",
    "https://www.njuskalo.hr/image-xlsize/nekretnine/kuca-zagreb-planina-donja-90.00-m2-slika-248570272.jpg",
    "https://www.njuskalo.hr/image-xlsize/nekretnine/kuca-zagreb-planina-donja-90.00-m2-slika-248570284.jpg",
    "https://www.njuskalo.hr/image-xlsize/nekretnine/kuca-zagreb-planina-donja-90.00-m2-slika-248570294.jpg",
    "https://www.njuskalo.hr/image-xlsize/nekretnine/kuca-zagreb-planina-donja-90.00-m2-slika-248570298.jpg",
    "https://www.njuskalo.hr/image-xlsize/nekretnine/kuca-zagreb-planina-donja-90.00-m2-slika-248570299.jpg",
    "https://www.njuskalo.hr/image-xlsize/nekretnine/kuca-zagreb-planina-donja-90.00-m2-slika-248570300.jpg",
    "https://www.njuskalo.hr/image-xlsize/nekretnine/kuca-zagreb-planina-donja-90.00-m2-slika-248570301.jpg",
    "https://www.njuskalo.hr/image-xlsize/nekretnine/kuca-zagreb-planina-donja-90.00-m2-slika-248570304.jpg",
    "https://www.njuskalo.hr/image-xlsize/nekretnine/kuca-zagreb-planina-donja-90.00-m2-slika-248570307.jpg",
    "https://www.njuskalo.hr/image-xlsize/nekretnine/kuca-zagreb-planina-donja-90.00-m2-slika-248570308.jpg"
  ]
}